ssh_config_json/__init__.py
ssh_config_json/config.py
ssh_config_json/encrypt.py
ssh_config_json/main.py
ssh_config_json-1.0.1.dist-info/LICENSE
ssh_config_json-1.0.1.dist-info/METADATA
ssh_config_json-1.0.1.dist-info/WHEEL
ssh_config_json-1.0.1.dist-info/entry_points.txt
ssh_config_json-1.0.1.dist-info/top_level.txt
ssh_config_json-1.0.1.dist-info/RECORD
