Metadata-Version: 2.1
Name: ssh-config-json
Version: 1.0.1
Summary: Dump JSON for your ssh config include IdentityFiles and restore those.
Home-page: https://github.com/tubone24/ssh_config_json
Author: tubone24
Author-email: tubo.yyyuuu@gmail.com
License: MIT
Project-URL: Documentation, https://ssh-config-json.readthedocs.io/en/latest/
Project-URL: ProjectBlog, https://blog.tubone-project24.xyz
Keywords: ssh-config,json,backup,AES
Platform: any
Classifier: Development Status :: 4 - Beta
Classifier: Intended Audience :: Developers
Classifier: License :: OSI Approved :: MIT License
Classifier: Operating System :: OS Independent
Classifier: Topic :: Documentation :: Sphinx
Classifier: Topic :: System :: Archiving :: Backup
Classifier: Programming Language :: Python
Classifier: Programming Language :: Python :: 3.6
Classifier: Programming Language :: Python :: 3.7
Classifier: Programming Language :: Python :: 3.8
Requires-Python: >=3.6
Requires-Dist: docopt (==0.6.2)
Requires-Dist: pycryptodome (==3.9.9)
Provides-Extra: develop
Requires-Dist: black (==19.10b0) ; extra == 'develop'
Requires-Dist: pytest (==5.2.3) ; extra == 'develop'
Requires-Dist: pytest-cov (==2.7.1) ; extra == 'develop'
Requires-Dist: pytest-pythonpath (==0.7.3) ; extra == 'develop'
Requires-Dist: flake8 (==3.7.7) ; extra == 'develop'
Requires-Dist: pep8 (==1.7.1) ; extra == 'develop'
Requires-Dist: pytest-flake8 (==1.0.4) ; extra == 'develop'
Requires-Dist: pytest-pep8 (==1.0.6) ; extra == 'develop'
Requires-Dist: coverage (==4.5.4) ; extra == 'develop'
Requires-Dist: twine (==3.2.0) ; extra == 'develop'
Requires-Dist: wheel (==0.35.1) ; extra == 'develop'
Provides-Extra: docs
Requires-Dist: mkdocs (==1.1.2) ; extra == 'docs'
